Metadata-Version: 2.1
Name: django-sotp
Version: 1.0
Summary: Generate a secured base32 one time password to authenticate your user! 🔐
Home-page: https://github.com/israelabraham/django-sopt
Author: Abram 🐼
Author-email: israelvictory87@gmail.com
License: CC0 1.0 Universal (CC0 1.0) Public Domain Dedication
Keywords: sotp,otp,totps,one time password,passwords
Platform: UNKNOWN
Classifier: Development Status :: 5 - Production/Stable
Classifier: Framework :: Django
Classifier: Framework :: Django :: 2.2
Classifier: Framework :: Django :: 3.0
Classifier: Framework :: Django :: 3.1
Classifier: Framework :: Django :: 3.2
Classifier: Framework :: Django :: 4.0
Classifier: Intended Audience :: Developers
Classifier: License :: CC0 1.0 Universal (CC0 1.0) Public Domain Dedication
Classifier: Programming Language :: Python
Classifier: Programming Language :: Python :: 3
Classifier: Programming Language :: Python :: 3 :: Only
Classifier: Programming Language :: Python :: 3.6
Classifier: Programming Language :: Python :: 3.7
Classifier: Programming Language :: Python :: 3.8
Classifier: Programming Language :: Python :: 3.9
Classifier: Programming Language :: Python :: 3.10
Classifier: Topic :: Software Development :: Build Tools
Requires-Python: >=3.6
Requires-Dist: django-apscheduler
Requires-Dist: django (>=2.2)
